{"timestamp": "2018-01-21 01:35:14.088448", "userid": "5a645e905c2b1", "history": [{"c": ["I am trying to understand your genre preferences."], "u": ["action"]}, {"c": ["Tell me some actors you like."], "u": ["will smith"]}, {"c": ["who is your favorite director?"], "u": ["stephen speilberg"]}, {"c": ["What MPAA rating should this movie be (eg. PG-13, pg, G)?", "There is no exact match for what was specified, so I will do my best!"], "u": ["r"]}, {"c": ["I'm thinking about what you might like.", "How about Enemy of the State (1998)? ", "Enemy of the State stars Tony Scott, Harry Gregson-Williams, Dan Mindel, Trevor Rabin, Will Smith, Gene Hackman, Jon Voight, Lisa Bonet, David Marconi, Jerry Bruckheimer and is directed by David Marconi.", "This film is 132 minutes long. It is an action, crime and mystery movie, and is rated R.", "Is this recommendation satisfactory?"], "u": ["yes"]}, {"c": ["", "Bye! Please click the next button to proceed."], "u": []}]}
