{"timestamp": "2018-01-22 18:31:17.904920", "userid": "5a669e162cc41", "history": [{"c": ["Tell me a genre you prefer?"], "u": ["documentary"]}, {"c": ["Can you tell me some actors or actresses you prefer to watch?"], "u": ["morgan freeman"]}, {"c": ["who is your favorite director?", "There is no exact match for what was specified, so I will do my best!"], "u": ["speilberg"]}, {"c": ["What MPAA rating should this movie be (eg. PG-13, pg, G)?"], "u": ["any"]}, {"c": ["I'm thinking about what you might like.", "How about Bowling for Columbine (2002)? ", "Bowling for Columbine stars Marilyn Manson, Kurt Engfehr, Jim Czarnecki, Charles Bishop, Salvador Allende, Jeff Gibbs, Michael Moore, Michael Donovan, Kathleen Glynn, Charlton Heston and is directed by Michael Moore.", "This film is 120 minutes long. It is a crime, documentary and drama movie, and is rated R.", "Is this recommendation satisfactory?"], "u": ["yes"]}, {"c": ["", "Bye! Please click the next button to proceed."], "u": []}]}
